{
  "posts": [
    {
      "id": 1,
      "title": "json-server",
      "author": "typicode"
    }
  ],
  "comments": [
    {
      "id": 1,
      "body": "some comment",
      "postId": 1
    }
  ],
  "profile": {
    "name": "typicode"
  },
  "contacts": [
    {
      "id": 26,
      "name": "Grant Berg",
      "email": "grantberg@unq.com",
      "phone": "+1 (837) 554-3706"
    },
    {
      "id": 27,
      "name": "Hawkins Winters",
      "email": "hawkinswinters@unq.com",
      "phone": "+1 (945) 469-2432"
    },
    {
      "id": 28,
      "name": "Frazier Davidson",
      "email": "frazierdavidson@unq.com",
      "phone": "+1 (854) 558-2637"
    },
    {
      "name": "Jahongir Xasanov",
      "email": "Rufathasanov1998@gmail.com",
      "phone": "+998936611222",
      "id": 29
    },
    {
      "name": "Javohir Xasanov",
      "email": "Rufathasanov1998@gmail.com",
      "phone": "+998935661198",
      "id": 30
    },
    {
      "name": "Rufat Xasanov",
      "email": "Rufathasanov1998@gmail.com",
      "phone": "+998935661198",
      "id": 31
    }
  ]
}